debouncer.v
module debouncer(
    input wire clk,
    input wire rst,
    input wire btn_raw,
    output reg btn_clean

);

reg [6:0] counter;
reg current_state, prev_input;

parameter norepeats = 1'b0,
          repeats   = 1'b1;

always @(posedge clk, negedge rst) begin

    if(!rst) begin
        counter <= 0;
        current_state <= norepeats;
        btn_clean <= btn_raw;
    end else begin

        

        case(current_state)

        
            norepeats: begin
                if (btn_raw != btn_clean) begin
                    current_state <= repeats;
                    prev_input <= btn_raw;
                end 
            end


            repeats: begin 
                if (prev_input == btn_raw) begin
                    counter <= counter + 1;
                    if (counter == 100) begin
                        btn_clean <= btn_raw;
                        counter <= 0;
                        current_state <= norepeats;
                    end
                end
                else begin
                    counter <= 0;
                    current_state <= norepeats;
                end
                    
                
            end

            
        endcase
    end

    
end




endmodule

debouncer_tb.v
module debouncer_tb;

reg clk, rst, btn_raw;
wire btn_clean;

debouncer DUT (
    .clk(clk),
    .rst(rst),
    .btn_raw(btn_raw),
    .btn_clean(btn_clean)
);

initial clk = 0;
always #5 clk = ~clk;

initial begin


    $dumpfile("debouncer.vcd");
    $dumpvars(0, debouncer_tb);
    

    rst = 0;
    btn_raw = 1;

    #50;
    rst = 1;

    #50;
    btn_raw = 0;

    #1500;
    btn_raw = 1;

    #1500;
    $finish ;

end

initial begin
    $monitor("[time = %0t] rst=%b btn_raw=%b btn_clean=%b", $time, rst, btn_raw, btn_clean);
end



endmodule

debouncer.vcd
$date
	Fri May 01 07:09:51 2026
$end
$version
	Icarus Verilog
$end
$timescale
	1s
$end
$scope module debouncer_tb $end
$var wire 1 ! btn_clean $end
$var reg 1 " btn_raw $end
$var reg 1 # clk $end
$var reg 1 $ rst $end
$scope module DUT $end
$var wire 1 " btn_raw $end
$var wire 1 # clk $end
$var wire 1 $ rst $end
$var parameter 1 % norepeats $end
$var parameter 1 & repeats $end
$var reg 1 ! btn_clean $end
$var reg 7 ' counter [6:0] $end
$var reg 1 ( current_state $end
$var reg 1 ) prev_input $end
$upscope $end
$upscope $end
$enddefinitions $end
$comment Show the parameter values. $end
$dumpall
1&
0%
$end
#0
$dumpvars
x)
0(
b0 '
0$
0#
1"
1!
$end
#5
1#
#10
0#
#15
1#
#20
0#
#25
1#
#30
0#
#35
1#
#40
0#
#45
1#
#50
0#
1$
#55
1#
#60
0#
#65
1#
#70
0#
#75
1#
#80
0#
#85
1#
#90
0#
#95
1#
#100
0#
0"
#105
0)
1(
1#
#110
0#
#115
b1 '
1#
#120
0#
#125
b10 '
1#
#130
0#
#135
b11 '
1#
#140
0#
#145
b100 '
1#
#150
0#
#155
b101 '
1#
#160
0#
#165
b110 '
1#
#170
0#
#175
b111 '
1#
#180
0#
#185
b1000 '
1#
#190
0#
#195
b1001 '
1#
#200
0#
#205
b1010 '
1#
#210
0#
#215
b1011 '
1#
#220
0#
#225
b1100 '
1#
#230
0#
#235
b1101 '
1#
#240
0#
#245
b1110 '
1#
#250
0#
#255
b1111 '
1#
#260
0#
#265
b10000 '
1#
#270
0#
#275
b10001 '
1#
#280
0#
#285
b10010 '
1#
#290
0#
#295
b10011 '
1#
#300
0#
#305
b10100 '
1#
#310
0#
#315
b10101 '
1#
#320
0#
#325
b10110 '
1#
#330
0#
#335
b10111 '
1#
#340
0#
#345
b11000 '
1#
#350
0#
#355
b11001 '
1#
#360
0#
#365
b11010 '
1#
#370
0#
#375
b11011 '
1#
#380
0#
#385
b11100 '
1#
#390
0#
#395
b11101 '
1#
#400
0#
#405
b11110 '
1#
#410
0#
#415
b11111 '
1#
#420
0#
#425
b100000 '
1#
#430
0#
#435
b100001 '
1#
#440
0#
#445
b100010 '
1#
#450
0#
#455
b100011 '
1#
#460
0#
#465
b100100 '
1#
#470
0#
#475
b100101 '
1#
#480
0#
#485
b100110 '
1#
#490
0#
#495
b100111 '
1#
#500
0#
#505
b101000 '
1#
#510
0#
#515
b101001 '
1#
#520
0#
#525
b101010 '
1#
#530
0#
#535
b101011 '
1#
#540
0#
#545
b101100 '
1#
#550
0#
#555
b101101 '
1#
#560
0#
#565
b101110 '
1#
#570
0#
#575
b101111 '
1#
#580
0#
#585
b110000 '
1#
#590
0#
#595
b110001 '
1#
#600
0#
#605
b110010 '
1#
#610
0#
#615
b110011 '
1#
#620
0#
#625
b110100 '
1#
#630
0#
#635
b110101 '
1#
#640
0#
#645
b110110 '
1#
#650
0#
#655
b110111 '
1#
#660
0#
#665
b111000 '
1#
#670
0#
#675
b111001 '
1#
#680
0#
#685
b111010 '
1#
#690
0#
#695
b111011 '
1#
#700
0#
#705
b111100 '
1#
#710
0#
#715
b111101 '
1#
#720
0#
#725
b111110 '
1#
#730
0#
#735
b111111 '
1#
#740
0#
#745
b1000000 '
1#
#750
0#
#755
b1000001 '
1#
#760
0#
#765
b1000010 '
1#
#770
0#
#775
b1000011 '
1#
#780
0#
#785
b1000100 '
1#
#790
0#
#795
b1000101 '
1#
#800
0#
#805
b1000110 '
1#
#810
0#
#815
b1000111 '
1#
#820
0#
#825
b1001000 '
1#
#830
0#
#835
b1001001 '
1#
#840
0#
#845
b1001010 '
1#
#850
0#
#855
b1001011 '
1#
#860
0#
#865
b1001100 '
1#
#870
0#
#875
b1001101 '
1#
#880
0#
#885
b1001110 '
1#
#890
0#
#895
b1001111 '
1#
#900
0#
#905
b1010000 '
1#
#910
0#
#915
b1010001 '
1#
#920
0#
#925
b1010010 '
1#
#930
0#
#935
b1010011 '
1#
#940
0#
#945
b1010100 '
1#
#950
0#
#955
b1010101 '
1#
#960
0#
#965
b1010110 '
1#
#970
0#
#975
b1010111 '
1#
#980
0#
#985
b1011000 '
1#
#990
0#
#995
b1011001 '
1#
#1000
0#
#1005
b1011010 '
1#
#1010
0#
#1015
b1011011 '
1#
#1020
0#
#1025
b1011100 '
1#
#1030
0#
#1035
b1011101 '
1#
#1040
0#
#1045
b1011110 '
1#
#1050
0#
#1055
b1011111 '
1#
#1060
0#
#1065
b1100000 '
1#
#1070
0#
#1075
b1100001 '
1#
#1080
0#
#1085
b1100010 '
1#
#1090
0#
#1095
b1100011 '
1#
#1100
0#
#1105
b1100100 '
1#
#1110
0#
#1115
0(
0!
b0 '
1#
