debouncer.v
module debouncer(
    input wire clk,
    input wire rst,
    input wire btn_raw,
    output reg btn_clean

);

reg [6:0] counter;
reg current_state, prev_input;

parameter norepeats = 1'b0,
          repeats   = 1'b1;

always @(posedge clk, negedge rst) begin

    if(!rst) begin
        counter <= 0;
        current_state <= norepeats;
        btn_clean <= btn_raw;
    end else begin

        

        case(current_state)

        
            norepeats: begin
                if (btn_raw != btn_clean) begin
                    current_state <= repeats;
                    prev_input <= btn_raw;
                end 
            end


            repeats: begin 
                if (prev_input == btn_raw) begin
                    counter <= counter + 1;
                    if (counter == 100) begin
                        btn_clean <= btn_raw;
                        counter <= 0;
                        current_state <= norepeats;
                    end
                end
                else begin
                    counter <= 0;
                    current_state <= norepeats;
                end
                    
                
            end

            
        endcase
    end

    
end




endmodule

debouncer_tb.v
module debouncer_tb;

reg clk, rst, btn_raw;
wire btn_clean;

debouncer DUT (
    .clk(clk),
    .rst(rst),
    .btn_raw(btn_raw),
    .btn_clean(btn_clean)
);

initial clk = 0;
always #5 clk = ~clk;
integer i;

initial begin


    $dumpfile("debouncer.vcd");
    $dumpvars(0, debouncer_tb);
    

    rst = 0;
    btn_raw = 1;

    #50;
    rst = 1;

    for (i = 0; i < 50; i = i + 1) begin
        btn_raw = ~btn_raw;
        #20;
    end

    btn_raw = 0;

    #1500;

    for (i = 0; i < 50; i = i + 1) begin
        btn_raw = ~btn_raw;
        #20;
    end

    btn_raw = 1;

    #1500;
    $finish ;

end

initial begin
    $monitor("[time = %0t] rst=%b btn_raw=%b btn_clean=%b", $time, rst, btn_raw, btn_clean);
end



endmodule

debouncer.vcd
$date
	Fri May 01 20:17:05 2026
$end
$version
	Icarus Verilog
$end
$timescale
	1s
$end
$scope module debouncer_tb $end
$var wire 1 ! btn_clean $end
$var reg 1 " btn_raw $end
$var reg 1 # clk $end
$var reg 1 $ rst $end
$var integer 32 % i [31:0] $end
$scope module DUT $end
$var wire 1 " btn_raw $end
$var wire 1 # clk $end
$var wire 1 $ rst $end
$var parameter 1 & norepeats $end
$var parameter 1 ' repeats $end
$var reg 1 ! btn_clean $end
$var reg 7 ( counter [6:0] $end
$var reg 1 ) current_state $end
$var reg 1 * prev_input $end
$upscope $end
$upscope $end
$enddefinitions $end
$comment Show the parameter values. $end
$dumpall
1'
0&
$end
#0
$dumpvars
x*
0)
b0 (
bx %
0$
0#
1"
1!
$end
#5
1#
#10
0#
#15
1#
#20
0#
#25
1#
#30
0#
#35
1#
#40
0#
#45
1#
#50
0#
0"
b0 %
1$
#55
0*
1)
1#
#60
0#
#65
b1 (
1#
#70
0#
1"
b1 %
#75
0)
b0 (
1#
#80
0#
#85
1#
#90
0#
0"
b10 %
#95
1)
1#
#100
0#
#105
b1 (
1#
#110
0#
1"
b11 %
#115
0)
b0 (
1#
#120
0#
#125
1#
#130
0#
0"
b100 %
#135
1)
1#
#140
0#
#145
b1 (
1#
#150
0#
1"
b101 %
#155
0)
b0 (
1#
#160
0#
#165
1#
#170
0#
0"
b110 %
#175
1)
1#
#180
0#
#185
b1 (
1#
#190
0#
1"
b111 %
#195
0)
b0 (
1#
#200
0#
#205
1#
#210
0#
0"
b1000 %
#215
1)
1#
#220
0#
#225
b1 (
1#
#230
0#
1"
b1001 %
#235
0)
b0 (
1#
#240
0#
#245
1#
#250
0#
0"
b1010 %
#255
1)
1#
#260
0#
#265
b1 (
1#
#270
0#
1"
b1011 %
#275
0)
b0 (
1#
#280
0#
#285
1#
#290
0#
0"
b1100 %
#295
1)
1#
#300
0#
#305
b1 (
1#
#310
0#
1"
b1101 %
#315
0)
b0 (
1#
#320
0#
#325
1#
#330
0#
0"
b1110 %
#335
1)
1#
#340
0#
#345
b1 (
1#
#350
0#
1"
b1111 %
#355
0)
b0 (
1#
#360
0#
#365
1#
#370
0#
0"
b10000 %
#375
1)
1#
#380
0#
#385
b1 (
1#
#390
0#
1"
b10001 %
#395
0)
b0 (
1#
#400
0#
#405
1#
#410
0#
0"
b10010 %
#415
1)
1#
#420
0#
#425
b1 (
1#
#430
0#
1"
b10011 %
#435
0)
b0 (
1#
#440
0#
#445
1#
#450
0#
0"
b10100 %
#455
1)
1#
#460
0#
#465
b1 (
1#
#470
0#
1"
b10101 %
#475
0)
b0 (
1#
#480
0#
#485
1#
#490
0#
0"
b10110 %
#495
1)
1#
#500
0#
#505
b1 (
1#
#510
0#
1"
b10111 %
#515
0)
b0 (
1#
#520
0#
#525
1#
#530
0#
0"
b11000 %
#535
1)
1#
#540
0#
#545
b1 (
1#
#550
0#
1"
b11001 %
#555
0)
b0 (
1#
#560
0#
#565
1#
#570
0#
0"
b11010 %
#575
1)
1#
#580
0#
#585
b1 (
1#
#590
0#
1"
b11011 %
#595
0)
b0 (
1#
#600
0#
#605
1#
#610
0#
0"
b11100 %
#615
1)
1#
#620
0#
#625
b1 (
1#
#630
0#
1"
b11101 %
#635
0)
b0 (
1#
#640
0#
#645
1#
#650
0#
0"
b11110 %
#655
1)
1#
#660
0#
#665
b1 (
1#
#670
0#
1"
b11111 %
#675
0)
b0 (
1#
#680
0#
#685
1#
#690
0#
0"
b100000 %
#695
1)
1#
#700
0#
#705
b1 (
1#
#710
0#
1"
b100001 %
#715
0)
b0 (
1#
#720
0#
#725
1#
#730
0#
0"
b100010 %
#735
1)
1#
#740
0#
#745
b1 (
1#
#750
0#
1"
b100011 %
#755
0)
b0 (
1#
#760
0#
#765
1#
#770
0#
0"
b100100 %
#775
1)
1#
#780
0#
#785
b1 (
1#
#790
0#
1"
b100101 %
#795
0)
b0 (
1#
#800
0#
#805
1#
#810
0#
0"
b100110 %
#815
1)
1#
#820
0#
#825
b1 (
1#
#830
0#
1"
b100111 %
#835
0)
b0 (
1#
#840
0#
#845
1#
#850
0#
0"
b101000 %
#855
1)
1#
#860
0#
#865
b1 (
1#
#870
0#
1"
b101001 %
#875
0)
b0 (
1#
#880
0#
#885
1#
#890
0#
0"
b101010 %
#895
1)
1#
#900
0#
#905
b1 (
1#
#910
0#
1"
b101011 %
#915
0)
b0 (
1#
#920
0#
#925
1#
#930
0#
0"
b101100 %
#935
1)
1#
#940
0#
#945
b1 (
1#
#950
0#
1"
b101101 %
#955
0)
b0 (
1#
#960
0#
#965
1#
#970
0#
0"
b101110 %
#975
1)
1#
#980
0#
#985
b1 (
1#
#990
0#
1"
b101111 %
#995
0)
b0 (
1#
#1000
0#
#1005
1#
#1010
0#
0"
b110000 %
#1015
1)
1#
#1020
0#
#1025
b1 (
1#
#1030
0#
1"
b110001 %
#1035
0)
b0 (
1#
#1040
0#
#1045
1#
#1050
0#
0"
b110010 %
#1055
1)
1#
#1060
0#
#1065
b1 (
1#
#1070
0#
#1075
b10 (
1#
#1080
0#
#1085
b11 (
1#
#1090
0#
#1095
b100 (
1#
#1100
0#
#1105
b101 (
1#
#1110
0#
#1115
b110 (
1#
#1120
0#
#1125
b111 (
1#
#1130
0#
#1135
b1000 (
1#
#1140
0#
#1145
b1001 (
1#
#1150
0#
#1155
b1010 (
1#
#1160
0#
#1165
b1011 (
1#
#1170
0#
#1175
b1100 (
1#
#1180
0#
#1185
b1101 (
1#
#1190
0#
#1195
b1110 (
1#
#1200
0#
#1205
b1111 (
1#
#1210
0#
#1215
b10000 (
1#
#1220
0#
#1225
b10001 (
1#
#1230
0#
#1235
b10010 (
1#
#1240
0#
#1245
b10011 (
1#
#1250
0#
#1255
b10100 (
1#
#1260
0#
#1265
b10101 (
1#
#1270
0#
#1275
b10110 (
1#
#1280
0#
#1285
b10111 (
1#
#1290
0#
#1295
b11000 (
1#
#1300
0#
#1305
b11001 (
1#
#1310
0#
#1315
b11010 (
1#
#1320
0#
#1325
b11011 (
1#
#1330
0#
#1335
b11100 (
1#
#1340
0#
#1345
b11101 (
1#
#1350
0#
#1355
b11110 (
1#
#1360
0#
#1365
b11111 (
1#
#1370
0#
#1375
b100000 (
1#
#1380
0#
#1385
b100001 (
1#
#1390
0#
#1395
b100010 (
1#
#1400
0#
#1405
b100011 (
1#
#1410
0#
#1415
b100100 (
1#
#1420
0#
#1425
b100101 (
1#
#1430
0#
#1435
b100110 (
1#
#1440
0#
#1445
b100111 (
1#
#1450
0#
#1455
b101000 (
1#
#1460
0#
#1465
b101001 (
1#
#1470
0#
#1475
b101010 (
1#
#1480
0#
#1485
b101011 (
1#
#1490
0#
#1495
b101100 (
1#
#1500
0#
#1505
b101101 (
1#
#1510
0#
#1515
b101110 (
1#
#1520
0#
#1525
b101111 (
1#
#1530
0#
#1535
b110000 (
1#
#1540
0#
#1545
b110001 (
1#
#1550
0#
#1555
b110010 (
1#
#1560
0#
#1565
b110011 (
1#
#1570
0#
#1575
b110100 (
1#
#1580
0#
#1585
b110101 (
1#
#1590
0#
#1595
b110110 (
1#
#1600
0#
#1605
b110111 (
1#
#1610
0#
#1615
b111000 (
1#
#1620
0#
#1625
b111001 (
1#
#1630
0#
#1635
b111010 (
1#
#1640
0#
#1645
b111011 (
1#
#1650
0#
#1655
b111100 (
1#
#1660
0#
#1665
b111101 (
1#
#1670
0#
#1675
b111110 (
1#
#1680
0#
#1685
b111111 (
1#
#1690
0#
#1695
b1000000 (
1#
#1700
0#
#1705
b1000001 (
1#
#1710
0#
#1715
b1000010 (
1#
#1720
0#
#1725
b1000011 (
1#
#1730
0#
#1735
b1000100 (
1#
#1740
0#
#1745
b1000101 (
1#
#1750
0#
#1755
b1000110 (
1#
#1760
0#
#1765
b1000111 (
1#
#1770
0#
#1775
b1001000 (
1#
#1780
0#
#1785
b1001001 (
1#
#1790
0#
#1795
b1001010 (
1#
#1800
0#
#1805
b1001011 (
1#
#1810
0#
#1815
b1001100 (
1#
#1820
0#
#1825
b1001101 (
1#
#1830
0#
#1835
b1001110 (
1#
#1840
0#
#1845
b1001111 (
1#
#1850
0#
#1855
b1010000 (
1#
#1860
0#
#1865
b1010001 (
1#
#1870
0#
#1875
b1010010 (
1#
#1880
0#
#1885
b1010011 (
1#
#1890
0#
#1895
b1010100 (
1#
#1900
0#
#1905
b1010101 (
1#
#1910
0#
#1915
b1010110 (
1#
#1920
0#
#1925
b1010111 (
1#
#1930
0#
#1935
b1011000 (
1#
#1940
0#
#1945
b1011001 (
1#
#1950
0#
#1955
b1011010 (
1#
#1960
0#
#1965
b1011011 (
1#
#1970
0#
#1975
b1011100 (
1#
#1980
0#
#1985
b1011101 (
1#
#1990
0#
#1995
b1011110 (
1#
#2000
0#
#2005
b1011111 (
1#
#2010
0#
#2015
b1100000 (
1#
#2020
0#
#2025
b1100001 (
1#
#2030
0#
#2035
b1100010 (
1#
#2040
0#
#2045
b1100011 (
1#
#2050
0#
#2055
b1100100 (
1#
#2060
0#
#2065
0)
0!
b0 (
1#
